available/checker.py
available/fingerprints.py
dom_available-0.1.4.dist-info/WHEEL
dom_available-0.1.4.dist-info/METADATA
dom_available-0.1.4.dist-info/RECORD
