Metadata-Version: 2.1
Name: dom-available
Version: 0.1.4
Summary: 
Author: Aman Jha
Author-email: amanjha22@gmail.com
Requires-Python: >=3.7,<4.0
Classifier: Programming Language :: Python :: 3
Classifier: Programming Language :: Python :: 3.7
Classifier: Programming Language :: Python :: 3.8
Classifier: Programming Language :: Python :: 3.9
Classifier: Programming Language :: Python :: 3.10
